README.rst
msgq.py
setup.cfg
setup.py
msgq.egg-info/PKG-INFO
msgq.egg-info/SOURCES.txt
msgq.egg-info/dependency_links.txt
msgq.egg-info/top_level.txt