Metadata-Version: 1.0
Name: msgq
Version: 0.1.3
Summary: A simple System V msgq interface for linux IPC
Home-page: https://github.com/jj4jj/pymsgq
Author: jj4jj
Author-email: resc@vip.qq.com
License: MIT License
Keywords: system V msgq linux IPC msgsnd msgrcv msgget
Platform: UNKNOWN
